[
    {
        "id": 1,
        "nombre": "Bruno",
        "apellido": "Fabrizio",
        "telefono": "223699858",
        "email": "bruno@gmail.com",
        "password": "123",
        "tipo": 1,
        "alta": true,
        "listaMascotas": [
            {
                "id": 1,
                "nombre": "Pepe",
                "raza": "Golden",
                "tamanio": "Grande",
                "obervaciones": "Lindo",
                "rutaFoto": "1-asd.jpeg",
                "rutaVideo": null,
                "rutaPlanVacunas": null,
                "alta": true
            },
            {
                "id": 2,
                "nombre": "Yuumi",
                "raza": "Gato",
                "tamanio": "chiquita",
                "obervaciones": "linda",
                "rutaFoto": null,
                "rutaVideo": null,
                "rutaPlanVacunas": null,
                "alta": true
            },
            {
                "id": 3,
                "nombre": "dsf",
                "raza": "dsfdsf",
                "tamanio": "fds",
                "obervaciones": "fsd",
                "rutaFoto": "1-dsf.jpeg",
                "rutaVideo": null,
                "rutaPlanVacunas": null,
                "alta": true
            },
            {
                "id": 4,
                "nombre": "dfsf",
                "raza": "sdfsd",
                "tamanio": "dsff",
                "obervaciones": "dsff",
                "rutaFoto": "1-dfsf.jpeg",
                "rutaVideo": null,
                "rutaPlanVacunas": null,
                "alta": true
            }
        ],
        "listaReservas": []
    }
]